odoo/addons/quality_control_product_manufacturer/README.rst
odoo/addons/quality_control_product_manufacturer/__init__.py
odoo/addons/quality_control_product_manufacturer/__manifest__.py
odoo/addons/quality_control_product_manufacturer/i18n/it.po
odoo/addons/quality_control_product_manufacturer/i18n/quality_control_product_manufacturer.pot
odoo/addons/quality_control_product_manufacturer/models/__init__.py
odoo/addons/quality_control_product_manufacturer/models/qc_inspection.py
odoo/addons/quality_control_product_manufacturer/readme/CONTRIBUTORS.rst
odoo/addons/quality_control_product_manufacturer/readme/DESCRIPTION.rst
odoo/addons/quality_control_product_manufacturer/static/description/icon.png
odoo/addons/quality_control_product_manufacturer/static/description/index.html
odoo/addons/quality_control_product_manufacturer/views/qc_inspection_views.xml
odoo_addon_quality_control_product_manufacturer-16.0.1.1.0.2.dist-info/METADATA
odoo_addon_quality_control_product_manufacturer-16.0.1.1.0.2.dist-info/WHEEL
odoo_addon_quality_control_product_manufacturer-16.0.1.1.0.2.dist-info/top_level.txt
odoo_addon_quality_control_product_manufacturer-16.0.1.1.0.2.dist-info/RECORD
