Metadata-Version: 2.1
Name: odoo-addon-quality_control_product_manufacturer
Version: 16.0.1.1.0.2
Summary: Provides information related to Manufacturer under Inspection
Home-page: https://github.com/OCA/manufacture
Author: Anusri Veerappan Prakasam, Odoo Community Association (OCA)
Author-email: support@odoo-community.org
License: AGPL-3
Classifier: Programming Language :: Python
Classifier: Framework :: Odoo
Classifier: Framework :: Odoo :: 16.0
Classifier: License :: OSI Approved :: GNU Affero General Public License v3
Requires-Python: >=3.10
Requires-Dist: odoo-addon-product-manufacturer<16.1dev,>=16.0dev
Requires-Dist: odoo-addon-quality-control-oca<16.1dev,>=16.0dev
Requires-Dist: odoo<16.1dev,>=16.0a
